statistika/__init__.py
statistika/_version.py
statistika/ols.py
statistika-0.0.1.dist-info/LICENSE
statistika-0.0.1.dist-info/METADATA
statistika-0.0.1.dist-info/WHEEL
statistika-0.0.1.dist-info/top_level.txt
statistika-0.0.1.dist-info/RECORD
